SwiftGUI/__init__.py
SwiftGUI/Base.py
SwiftGUI/BasePopup.py
SwiftGUI/Canvas_Elements/__init__.py
SwiftGUI/Canvas_Elements/_Base.py
SwiftGUI/Canvas_Elements/Arc.py
SwiftGUI/Canvas_Elements/Bitmap.py
SwiftGUI/Canvas_Elements/Element.py
SwiftGUI/Canvas_Elements/Image.py
SwiftGUI/Canvas_Elements/Line.py
SwiftGUI/Canvas_Elements/Oval.py
SwiftGUI/Canvas_Elements/Polygon.py
SwiftGUI/Canvas_Elements/Rectangle.py
SwiftGUI/Canvas_Elements/Text.py
SwiftGUI/Colors.py
SwiftGUI/Combined_Elements/BaseCombinedElement.py
SwiftGUI/Combined_Elements/Console.py
SwiftGUI/Combined_Elements/Form.py
SwiftGUI/Combined_Elements/MultistateButton.py
SwiftGUI/Compat.py
SwiftGUI/Debug.py
SwiftGUI/DecoratorKeys.py
SwiftGUI/ElementFlags.py
SwiftGUI/Events.py
SwiftGUI/Examples/__init__.py
SwiftGUI/Examples/AllElements.py
SwiftGUI/Examples/AllThemes.py
SwiftGUI/Examples/GlobalOptionBrowser.py
SwiftGUI/Examples/Previews.py
SwiftGUI/Extended_Elements/ColorChooserButton.py
SwiftGUI/Extended_Elements/FileBrowseButton.py
SwiftGUI/Extended_Elements/Image.py
SwiftGUI/Extended_Elements/ImageButton.py
SwiftGUI/Extended_Elements/Separator.py
SwiftGUI/Extended_Elements/Spacer.py
SwiftGUI/Extended_Elements/TabFrame.py
SwiftGUI/Extended_Elements/Table.py
SwiftGUI/Extras/__init__.py
SwiftGUI/Extras/SwiftGUI.py
SwiftGUI/Files/__init__.py
SwiftGUI/Files/ConfigFile.py
SwiftGUI/Files/ConfigurationEditor.py
SwiftGUI/Files/DictFile.py
SwiftGUI/Files/ProgramDirectory.py
SwiftGUI/Fonts.py
SwiftGUI/GlobalOptions.py
SwiftGUI/KeyFunctions.py
SwiftGUI/KeyManager.py
SwiftGUI/Literals.py
SwiftGUI/Popups/__init__.py
SwiftGUI/Popups/ElementPopup.py
SwiftGUI/Popups/ListPicker.py
SwiftGUI/Popups/Popups.py
SwiftGUI/Popups/VirtualKeyboard.py
SwiftGUI/Themes/__init__.py
SwiftGUI/Themes/_BaseTheme.py
SwiftGUI/Themes/FourColors.py
SwiftGUI/Themes/Thematic.py
SwiftGUI/Tools.py
SwiftGUI/Utilities/Images.py
SwiftGUI/Utilities/Threads.py
SwiftGUI/Widget_Elements/Button.py
SwiftGUI/Widget_Elements/Canvas.py
swiftgui-0.11.1.dist-info/LICENSE
swiftgui-0.11.1.dist-info/METADATA
swiftgui-0.11.1.dist-info/WHEEL
swiftgui-0.11.1.dist-info/RECORD
