Metadata-Version: 2.3
Name: SwiftGUI
Version: 0.11.1
Summary: An easy-to-use package for quickly creating smaller and bigger GUIs
License: Apache-2.0
Author: Eric aka CheesecakeTV
Author-email: cheesecaketv53+pypi@gmail.com
Requires-Python: >=3.10
Classifier: Programming Language :: Python :: 3
Classifier: Operating System :: OS Independent
Requires-Dist: datetime
Requires-Dist: pillow
Requires-Dist: pyperclip
Project-URL: Documentation, https://github.com/CheesecakeTV/SwiftGUI-Docs
Project-URL: Repository, https://github.com/CheesecakeTV/SwiftGUI
Project-URL: issues, https://github.com/CheesecakeTV/SwiftGUI/issues
